setup.py
Element_Locator/__init__.py
testless_elementlocator.egg-info/PKG-INFO
testless_elementlocator.egg-info/SOURCES.txt
testless_elementlocator.egg-info/dependency_links.txt
testless_elementlocator.egg-info/requires.txt
testless_elementlocator.egg-info/top_level.txt